pyflow/__init__.py
pyflow/cli.py
pyflow/core.py
pyflow/decorators.py
pyflow/generators/__init__.py
pyflow/generators/api_generator.py
pyflow/generators/client_generator.py
pyflow/generators/ts_generator.py
pyflow/utils/__init__.py
pyflow/utils/inspect_utils.py
pyflow/utils/type_converter.py
pyflow_ts-0.2.4.dist-info/LICENSE
pyflow_ts-0.2.4.dist-info/METADATA
pyflow_ts-0.2.4.dist-info/WHEEL
pyflow_ts-0.2.4.dist-info/entry_points.txt
pyflow_ts-0.2.4.dist-info/top_level.txt
pyflow_ts-0.2.4.dist-info/RECORD
