Metadata-Version: 2.2
Name: pyflow-ts
Version: 0.2.4
Summary: Bridge Python and TypeScript with ease
Author-email: ExtensityAI Team <support@extensity.ai>
License: MIT
Project-URL: Homepage, https://github.com/ExtensityAI/PyFlow.ts
Project-URL: Bug Tracker, https://github.com/ExtensityAI/PyFlow.ts/issues
Project-URL: Documentation, https://extensity.ai/PyFlow.ts
Keywords: typescript,api,code generation,bridge,web development
Classifier: Development Status :: 4 - Beta
Classifier: Intended Audience :: Developers
Classifier: License :: OSI Approved :: MIT License
Classifier: Programming Language :: Python :: 3
Classifier: Programming Language :: Python :: 3.10
Classifier: Programming Language :: Python :: 3.11
Classifier: Programming Language :: Python :: 3.12
Classifier: Programming Language :: JavaScript
Classifier: Topic :: Software Development :: Libraries :: Python Modules
Classifier: Topic :: Software Development :: Code Generators
Requires-Python: >=3.10
License-File: LICENSE
Requires-Dist: fastapi>=0.95.0
Requires-Dist: uvicorn>=0.21.0
Requires-Dist: pydantic>=1.10.7
Requires-Dist: typing-extensions>=4.5.0
Requires-Dist: requests>=2.28.2
